{
  "id": "a1b2c3d4-e5f6-7890-abcd-ef1234567890",
  "name": "Ticker (Tryb: Whip / Poziomy / Pionowy)",
  "type": "TICKER",
  "version": 1,
  "features": {
    "wiper": true,
    "ticker_mode": true
  },
  "html_template": "<div class=\"utk-container\">\n    <div class=\"utk-wiper\" {{#unless WIPER_SHOW}}style=\"display:none;\"{{/unless}}>\n        <div class=\"utk-wiper-gleam\"></div>\n        <span class=\"utk-wiper-text\">{{WIPER_TEXT}}</span>\n    </div>\n    <!-- Tryb: poziomy (scroll) -->\n    <div class=\"utk-track-wrap\" style=\"display:none;\">\n        <div class=\"utk-ticker-track\">\n            {{#if ITEMS}}\n                {{#each ITEMS}}\n                <div class=\"utk-ticker-item\">{{{this}}}</div>\n                <div class=\"utk-ticker-sep\"></div>\n                {{/each}}\n            {{else}}\n                <div class=\"utk-ticker-item\">ŁADOWANIE...</div>\n                <div class=\"utk-ticker-sep\"></div>\n            {{/if}}\n        </div>\n    </div>\n    <!-- Tryb: pionowy i whip (pojedynczy tekst) -->\n    <div class=\"utk-single-wrap\" style=\"display:none;\">\n        <div class=\"utk-viewport\">\n            <div class=\"utk-single-text\">{{#if ITEMS}}{{{ITEMS.[0]}}}{{else}}ŁADOWANIE...{{/if}}</div>\n        </div>\n    </div>\n    <div id=\"f-news-list\" style=\"display:none;\">{{ITEMS_JSON}}</div>\n</div>",
  "css_template": "#{{ID}} .utk-container {\n    position: absolute;\n    bottom: 0;\n    left: 0;\n    width: var(--v-width, 100%);\n    min-height: var(--v-height, 60px);\n    background: {{PRIMARY_BG}};\n    display: flex;\n    align-items: center;\n    overflow: hidden;\n    border: {{BORDER_WIDTH}}px solid {{BORDER_COLOR}};\n    border-radius: {{BORDER_RADIUS}}px;\n    box-sizing: border-box;\n    font-family: '{{FONT_FAMILY}}', sans-serif;\n    opacity: 0;\n    transform: translateY(100px);\n    box-shadow: {{BOX_SHADOW}};\n}\n/* --- WIPER --- */\n#{{ID}} .utk-wiper {\n    position: absolute;\n    left: 0;\n    min-width: 150px;\n    width: auto;\n    padding: 0 40px;\n    height: 100%;\n    background: {{WIPER_BG}};\n    display: flex;\n    align-items: center;\n    justify-content: center;\n    box-shadow: 5px 0 15px rgba(0,0,0,0.5);\n    border-radius: {{BORDER_RADIUS}}px;\n    z-index: 10;\n    box-sizing: border-box;\n    overflow: hidden;\n    flex-shrink: 0;\n}\n#{{ID}} .utk-wiper-gleam {\n    position: absolute;\n    top: 0;\n    left: -100%;\n    width: 60%;\n    height: 100%;\n    display: {{#if WIPER_GLEAM_ENABLED}}block{{else}}none{{/if}};\n    background: {{WIPER_GLEAM_BG}};\n    transform: skewX(-20deg);\n    pointer-events: none;\n    animation: utk-gleam {{WIPER_GLEAM_DURATION}}s infinite ease-in-out;\n}\n#{{ID}} .utk-wiper-text {\n    font-weight: {{WIPER_FONT_WEIGHT}};\n    font-size: {{WIPER_FONT_SIZE}}px;\n    font-family: {{WIPER_FONT}}, sans-serif;\n    color: {{WIPER_TEXT_COLOR}};\n    letter-spacing: {{WIPER_LETTER_SPACING}}px;\n    position: relative;\n    z-index: 1;\n    white-space: nowrap;\n}\n/* --- TRYB: POZIOMY (scroll) --- */\n#{{ID}} .utk-track-wrap {\n    flex: 1;\n    overflow: hidden;\n    height: 100%;\n    align-items: center;\n}\n#{{ID}} .utk-ticker-track {\n    display: flex;\n    align-items: center;\n    white-space: nowrap;\n    height: 100%;\n    padding-left: 100%;\n}\n#{{ID}} .utk-ticker-item {\n    color: {{TITLE_COLOR}};\n    font-size: {{TITLE_SIZE}}px;\n    font-weight: {{TITLE_WEIGHT}};\n    text-transform: {{TITLE_TRANSFORM}};\n    padding: {{PADDING_Y}}px 20px;\n    white-space: nowrap;\n}\n#{{ID}} .utk-ticker-sep {\n    {{SEPARATOR_CSS}}\n}\n/* --- TRYB: PIONOWY --- */\n#{{ID}} .utk-single-wrap {\n    flex: 1;\n    height: 100%;\n    position: relative;\n    overflow: hidden;\n}\n#{{ID}} .utk-viewport {\n    width: 100%;\n    height: 100%;\n    position: relative;\n    overflow: hidden;\n}\n#{{ID}} .utk-single-text {\n    position: absolute;\n    width: 100%;\n    height: 100%;\n    display: flex;\n    align-items: center;\n    padding: 0 20px;\n    box-sizing: border-box;\n    color: {{TITLE_COLOR}};\n    font-size: {{TITLE_SIZE}}px;\n    font-weight: {{TITLE_WEIGHT}};\n    text-transform: {{TITLE_TRANSFORM}};\n    white-space: nowrap;\n    transition: opacity 0.4s ease-in-out;\n    opacity: 0;\n}\n#{{ID}} .utk-single-text.visible {\n    opacity: 1;\n}\n/* --- WHIP ANIMATIONS --- */\n#{{ID}} .utk-wiper.move-right {\n    animation: utk-wiper-slide-right 1s linear forwards;\n}\n#{{ID}} .utk-wiper.snap-back {\n    animation: utk-wiper-snap-back 0.5s ease-in-out forwards;\n}\n@keyframes utk-wiper-slide-right {\n    0%   { left: 0%; }\n    100% { left: calc(var(--v-width, 100%) - var(--wiper-w, 170px)); }\n}\n@keyframes utk-wiper-snap-back {\n    0%   { left: calc(var(--v-width, 100%) - var(--wiper-w, 170px)); }\n    100% { left: 0%; }\n}\n@keyframes utk-gleam {\n    0%   { left: -100%; }\n    100% { left: 200%; }\n}",
  "js_template": "(() => {\n    const root = document.getElementById(\"{{ID}}\");\n    const container  = root.querySelector('.utk-container');\n    const wiper      = root.querySelector('.utk-wiper');\n    const wiperTextEl= root.querySelector('.utk-wiper-text');\n    const gleamEl    = root.querySelector('.utk-wiper-gleam');\n    const dataEl     = root.querySelector('#f-news-list');\n    const trackWrap  = root.querySelector('.utk-track-wrap');\n    const singleWrap = root.querySelector('.utk-single-wrap');\n    const singleText = root.querySelector('.utk-single-text');\n    const tickerTrack= root.querySelector('.utk-ticker-track');\n\n    if (!container || !dataEl) return;\n\n    const MODE = \"{{TICKER_MODE}}\" || \"whip\"; // whip | horizontal | vertical\n    const DEFAULT_WIPER = \"{{WIPER_TEXT}}\";\n    const WIPER_SHOW = \"{{WIPER_SHOW}}\" !== \"false\";\n\n    let items = [];\n    try { items = JSON.parse(dataEl.textContent || '[]'); } catch(e) { console.error('Error parsing ITEMS json', e); } \n    if (!items.length) items = ['BRAK WIADOMOŚCI'];\n\n    const getText = (item) => (typeof item === 'object') ? (item.text || '') : item;\n    const getCat  = (item) => (typeof item === 'object') ? (item.category || '') : '';\n\n    let currentIndex = 0;\n    let cycleRunning = false;\n    let activeTimeouts = [];\n    let cycleTimer = null;\n\n    // Ustaw widoczne panele\n    function setupLayout() {\n        if (MODE === 'horizontal') {\n            trackWrap.style.display  = 'flex';\n            singleWrap.style.display = 'none';\n        } else {\n            trackWrap.style.display  = 'none';\n            singleWrap.style.display = 'flex';\n        }\n    }\n\n    function getWiperWidth() {\n        return (wiper && wiper.style.display !== 'none') ? wiper.offsetWidth : 0;\n    }\n\n    function updateWiper(label) {\n        const show = WIPER_SHOW && !!(label && label.trim());\n        if (wiper) {\n            wiper.style.display = show ? 'flex' : 'none';\n            if (wiperTextEl) wiperTextEl.innerText = show ? label : '';\n        }\n        container.style.setProperty('--wiper-w', getWiperWidth() + 'px');\n    }\n\n    function adjustFontSingleText(el) {\n        const base = parseFloat(\"{{TITLE_SIZE}}\") || 40;\n        const wiperW = getWiperWidth();\n        const maxW = container.offsetWidth - wiperW - 40;\n        el.style.paddingLeft = (wiperW > 0 ? wiperW + 20 : 20) + 'px';\n        el.style.fontSize = base + 'px';\n        let newSize = base;\n        if (maxW > 0 && el.scrollWidth > maxW && el.scrollWidth > 0) {\n            newSize = Math.min((maxW / el.scrollWidth) * base, base);\n        }\n        el.style.fontSize = Math.max(newSize, 10) + 'px';\n    }\n\n    // ============ TRYB: WHIP ============\n    function runWhip() {\n        if (!cycleRunning) return;\n        singleText.classList.remove('visible');\n\n        const item = items[currentIndex];\n        const text = getText(item);\n        const cat  = getCat(item);\n        singleText.innerHTML = text;\n        const label = cat || DEFAULT_WIPER;\n        updateWiper(label);\n        adjustFontSingleText(singleText);\n\n        activeTimeouts.push(setTimeout(() => {\n            if (!cycleRunning) return;\n            singleText.classList.add('visible');\n        }, 100));\n\n        activeTimeouts.push(setTimeout(() => {\n            if (!cycleRunning) return;\n            singleText.classList.remove('visible');\n            activeTimeouts.push(setTimeout(() => {\n                if (!cycleRunning) return;\n                if (wiper && wiper.style.display !== 'none') {\n                    wiper.className = 'utk-wiper move-right';\n                }\n                activeTimeouts.push(setTimeout(() => {\n                    if (!cycleRunning) return;\n                    if (wiper && wiper.style.display !== 'none') {\n                        wiper.className = 'utk-wiper snap-back';\n                    }\n                    activeTimeouts.push(setTimeout(() => {\n                        if (!cycleRunning) return;\n                        currentIndex = (currentIndex + 1) % items.length;\n                        runWhip();\n                    }, 500));\n                }, 1000));\n            }, 400));\n        }, 4000));\n    }\n\n    // ============ TRYB: PIONOWY ============\n    function runVertical() {\n        if (!cycleRunning) return;\n        singleText.classList.remove('visible');\n\n        const item = items[currentIndex];\n        singleText.innerHTML = getText(item);\n        updateWiper(getCat(item) || DEFAULT_WIPER);\n        adjustFontSingleText(singleText);\n\n        const displayMs = Math.max(1000, (parseFloat(\"{{TICKER_SPEED}}\") || 5) * 1000);\n\n        activeTimeouts.push(setTimeout(() => {\n            if (!cycleRunning) return;\n            singleText.classList.add('visible');\n        }, 100));\n\n        cycleTimer = setTimeout(() => {\n            if (!cycleRunning) return;\n            singleText.classList.remove('visible');\n            setTimeout(() => {\n                if (!cycleRunning) return;\n                currentIndex = (currentIndex + 1) % items.length;\n                runVertical();\n            }, 500);\n        }, displayMs);\n    }\n\n    // ============ TRYB: POZIOMY ============\n    function runHorizontal() {\n        if (!tickerTrack) return;\n        const trackItems = Array.from(tickerTrack.querySelectorAll('.utk-ticker-item'));\n        const itemData = trackItems.map((el, idx) => ({\n            el: el,\n            offset: el.offsetLeft,\n            category: getCat(items[idx]) || DEFAULT_WIPER\n        }));\n        const trackWidth = tickerTrack.scrollWidth || 0;\n        const speedPxPerSec = parseFloat(\"{{TICKER_SPEED}}\") || parseFloat(\"{{speed}}\") || 100;\n        const triggerPoint = getWiperWidth() || 150;\n        let lastCategory = '';\n\n        // Ustaw wiper na pierwszą kategorię\n        const firstCat = (itemData[0] && itemData[0].category) || DEFAULT_WIPER;\n        updateWiper(firstCat);\n        lastCategory = firstCat;\n\n        if (speedPxPerSec > 0 && trackWidth > 0) {\n            const duration = trackWidth / speedPxPerSec;\n            gsap.to(tickerTrack, {\n                x: -trackWidth,\n                duration: duration,\n                ease: 'none',\n                repeat: -1,\n                onUpdate: function() {\n                    const currentX = gsap.getProperty(tickerTrack, 'x');\n                    let activeCat = DEFAULT_WIPER;\n                    for (let i = 0; i < itemData.length; i++) {\n                        if (currentX + itemData[i].offset > triggerPoint) {\n                            activeCat = itemData[i].category;\n                            break;\n                        }\n                    }\n                    if (activeCat !== lastCategory) {\n                        lastCategory = activeCat;\n                        updateWiper(activeCat);\n                    }\n                }\n            });\n        }\n    }\n\n    // ============ SHOWslt / HIDE ============\n    root.__slt_show = () => {\n        cycleRunning = true;\n        setupLayout();\n        const tl = gsap.timeline();\n        tl.to(container, { opacity: 1, y: 0, duration: 0.6, ease: 'power2.out' });\n        tl.add(() => {\n            if (MODE === 'whip')       runWhip();\n            else if (MODE === 'vertical')  runVertical();\n            else if (MODE === 'horizontal') runHorizontal();\n        }, '+=0.1');\n        return tl;\n    };\n\n    root.__slt_hide = () => {\n        cycleRunning = false;\n        activeTimeouts.forEach(t => clearTimeout(t));\n        activeTimeouts = [];\n        if (cycleTimer) clearTimeout(cycleTimer);\n        if (tickerTrack) gsap.killTweensOf(tickerTrack);\n        if (gleamEl) gsap.killTweensOf(gleamEl);\n        const tl = gsap.timeline();\n        tl.to(container, { opacity: 0, y: 100, duration: 0.4, ease: 'power2.in' });\n        return tl;\n    };\n\n    window.addEventListener('resize', () => {\n        if (MODE !== 'horizontal') adjustFontSingleText(singleText);\n    });\n})();",
  "defaultFields": {
    "items": [
      {
        "text": "PILNE: PREZYDENT K. NAWROCKI WETUJE USTAWĘ WS. PROGRAMU \"SAFE\"",
        "category": "PILNE"
      },
      {
        "text": "PREMIER D. TUSK OSTRO O WECIE: \"PREZES PIS POPROWADZIŁ GO JAK ZA RĄCZKĘ\"",
        "category": ""
      },
      {
        "text": "RUCH RZĄDU W ODPOWIEDZI NA WETO. JEST NOWA UCHWAŁA I UPOWAŻNIENIA DLA MINISTRÓW",
        "category": "INFO"
      },
      "SZEF ZWIĄZKÓW ZAWODOWYCH POLICJI ALARMUJE: LUDZIE LICZYLI NA ŚRODKI Z \"SAFE\"",
      "PILNE: ZMASOWANY ATAK USA NA IRAŃSKĄ WYSPĘ. \"JEDNO Z NAJSILNIEJSZYCH BOMBARDOWAŃ\""
    ],
    "tickerMode": "whip",
    "primaryColor": "#730000",
    "secondaryColor": "#ff0055",
    "titleColor": "#ffffff",
    "fontFamily": "Bahnschrift",
    "introText": "PILNE",
    "type": "TICKER",
    "name": "Ticker (Unified)",
    "speed": 5,
    "animation": {
      "in": {
        "type": "slide",
        "direction": "bottom",
        "duration": 0.6
      },
      "out": {
        "type": "slide",
        "direction": "bottom",
        "duration": 0.4
      }
    },
    "style": {
      "background": {
        "type": "gradient",
        "color": "#ffcc00",
        "borderRadius": 10,
        "borderWidth": 0,
        "borderColor": "#442c2c",
        "gradientAngle": 160,
        "color2": "#d3a012"
      },
      "typography": {
        "color": "#362626",
        "fontFamily": "Bahnschrift",
        "fontSize": 30,
        "fontWeight": "600",
        "textTransform": "uppercase"
      }
    },
    "accentColor": "#ff0055",
    "layout": {
      "layer": 5,
      "width": 1650,
      "x": 180,
      "side": "bottom-right",
      "marginY": 50,
      "marginX": 50,
      "height": "40"
    },
    "wiper": {
      "bgColor": "#901414",
      "fontSize": 30,
      "fontFamily": "Bahnschrift"
    }
  },
  "defaultStyle": {
    "background": {
      "type": "gradient",
      "color": "#ffcc00",
      "borderRadius": 10,
      "borderWidth": 0,
      "borderColor": "#442c2c",
      "gradientAngle": 160,
      "color2": "#d3a012"
    },
    "typography": {
      "color": "#362626",
      "fontFamily": "Bahnschrift",
      "fontSize": 30,
      "fontWeight": "600",
      "textTransform": "uppercase"
    }
  },
  "defaultAnimation": {
    "in": {
      "type": "slide",
      "direction": "bottom",
      "duration": 0.6
    },
    "out": {
      "type": "slide",
      "direction": "bottom",
      "duration": 0.4
    }
  },
  "defaultLayout": {
    "layer": 5,
    "width": 1650,
    "x": 180,
    "side": "bottom-right",
    "marginY": 50,
    "marginX": 50,
    "height": "40"
  }
}